Workbook
Name Slicer_Expense_Week: #N/A
Name Slicer_Week: #N/A

Sheet Dashboard

Sheet Cash Flow Forecast
A1: 13-WEEK CASH FLOW FORECAST
A3: Week | B3: Date Range | C3: Beginning | D3: Cash In | E3: Cash Out | F3: Net Cash Flow | G3: Ending
A4: Week 01 | B4: Dec 01 - Dec 07, 2026 | C4: 85000 | D4: ='Cash Inflow'!D3 -> 22000 | E4: ='Cash Outflow '!B19 -> 30860 | F4: =D4-E4 -> -8860 | G4: =C4+F4 -> 76140
A5: Week 02 | B5: Dec 08 - Dec 14, 2026 | C5: =G4 -> 76140 | D5: ='Cash Inflow'!D4 -> 16000 | E5: ='Cash Outflow '!B20 -> 15220 | F5: =D5-E5 -> 780 | G5: =C5+F5 -> 76920
A6: Week 03 | B6: Dec 15 - Dec 21, 2026 | C6: =G5 -> 76920 | D6: ='Cash Inflow'!D5 -> 12000 | E6: ='Cash Outflow '!B21 -> 24600 | F6: =D6-E6 -> -12600 | G6: =C6+F6 -> 64320
A7: Week 04 | B7: Dec 22 - Dec 28, 2026 | C7: =G6 -> 64320 | D7: ='Cash Inflow'!D6 -> 4000 | E7: ='Cash Outflow '!B22 -> 14800 | F7: =D7-E7 -> -10800 | G7: =C7+F7 -> 53520
A8: Week 05 | B8: Dec 29 - Jan 04, 2027 | C8: =G7 -> 53520 | D8: ='Cash Inflow'!D7 -> 16000 | E8: ='Cash Outflow '!B23 -> 30860 | F8: =D8-E8 -> -14860 | G8: =C8+F8 -> 38660
A9: Week 06 | B9: Jan 05 - Jan 11, 2027 | C9: =G8 -> 38660 | D9: ='Cash Inflow'!D8 -> 3760 | E9: ='Cash Outflow '!B24 -> 15220 | F9: =D9-E9 -> -11460 | G9: =C9+F9 -> 27200
A10: Week 07 | B10: Jan 12 - Jan 18, 2027 | C10: =G9 -> 27200 | D10: ='Cash Inflow'!D9 -> 6000 | E10: ='Cash Outflow '!B25 -> 23700 | F10: =D10-E10 -> -17700 | G10: =C10+F10 -> 9500
A11: Week 08 | B11: Jan 19 - Jan 25, 2027 | C11: =G10 -> 9500 | D11: ='Cash Inflow'!D10 -> 24000 | E11: ='Cash Outflow '!B26 -> 16900 | F11: =D11-E11 -> 7100 | G11: =C11+F11 -> 16600
A12: Week 09 | B12: Jan 26 - Feb 01, 2027 | C12: =G11 -> 16600 | D12: ='Cash Inflow'!D11 -> 31000 | E12: ='Cash Outflow '!B27 -> 30860 | F12: =D12-E12 -> 140 | G12: =C12+F12 -> 16740
A13: Week 10 | B13: Feb 02 - Feb 08, 2027 | C13: =G12 -> 16740 | D13: ='Cash Inflow'!D12 -> 16000 | E13: ='Cash Outflow '!B28 -> 14800 | F13: =D13-E13 -> 1200 | G13: =C13+F13 -> 17940
A14: Week 11 | B14: Feb 09 - Feb 15, 2027 | C14: =G13 -> 17940 | D14: ='Cash Inflow'!D13 -> 24000 | E14: ='Cash Outflow '!B29 -> 22920 | F14: =D14-E14 -> 1080 | G14: =C14+F14 -> 19020
A15: Week 12 | B15: Feb 16 - Feb 22, 2027 | C15: =G14 -> 19020 | D15: ='Cash Inflow'!D14 -> 16000 | E15: ='Cash Outflow '!B30 -> 16900 | F15: =D15-E15 -> -900 | G15: =C15+F15 -> 18120
A16: Week 13 | B16: Feb 23 - Mar 01, 2027 | C16: =G15 -> 18120 | D16: ='Cash Inflow'!D15 -> 20000 | E16: ='Cash Outflow '!B31 -> 19300 | F16: =D16-E16 -> 700 | G16: =C16+F16 -> 18820
C17: =C4 -> 85000 | D17: =SUM(D4:D16) -> 210760 | E17: =SUM(E4:E16) -> 276940 | F17: =SUM(F4:F16) -> -66180 | G17: =G16 -> 18820

Sheet Task
A1: MINI PROJECT: 13-WEEK CASH FLOW ANALYSIS
A2: Greenway Landscaping LLC | Cash Flow Forecast
B4: BACKGROUND
B5: Greenway Landscaping LLC is a landscaping services company. The CFO needs to know: over the next 13 weeks (12/01/2026 - 02/28/2027), will the company have enough cash, and which week is the most critical?
B6: Your task is to build a 13-WEEK CASH FLOW FORECAST from the 3 data sources provided in this file.
B7: DATA PROVIDED (see adjacent sheets)
B8: • Sheet 'Cash Position' : Opening cash balance: 85,000.00 (as of 11/30/2026).
B9: • Sheet 'AR Collections' : Cash CUSTOMERS will pay (cash IN) by week. Already summarized by week in the top section.
B10: • Sheet 'Committed Expenses' : Fixed EXPENSES (cash OUT): amount per occurrence, frequency, and due date.
B11: REQUIREMENTS
B12: 1) Complete the 'Cash Flow Forecast' sheet. For each week, fill in 5 columns: Beginning Balance, Cash In, Cash Out, Net Cash Flow, Ending Balance.
B13: 2) Cash In per week = pull from the 'AR Collections' sheet.
B14: 3) Cash Out per week = you must ALLOCATE each expense to the correct week based on frequency + due date (e.g., 'Monthly (1st)' falls in the week containing the 1st; 'Weekly' appears every week; 'Bi-weekly' every other week).
B15: 4) Core formula: Ending Balance = Beginning Balance + Cash In − Cash Out. And: Next week’s Beginning Balance = This week’s Ending Balance.

Sheet Answer
B2: ANALYSIS QUESTIONS
B3: a) Which week has the LOWEST cash balance? How much? Cash declines steadily from Week 1 (76,140) down to Week 7 because collections in the early weeks are thin - receivables typically take 1 to 2 months to come in, while payroll and fuel go out every single week.
B4: b) Is there any week with negative cash (cash shortfall)? If so, how much does the company need to borrow/prepare? No. The lowest balance is still positive at 9,500. The company does NOT need to borrow during this period. That said, the cushion is razor-thin, so it would be wise to keep a revolving credit line on standby in case customers pay late.
B5: c) Over the 13 weeks, what are the total Cash In and total Cash Out? Is the company accumulating or burning cash? Burning cash. Total inflows of 210,760 fall short of total outflows of 276,940, resulting in a net cash burn of -66,180 over 13 weeks. The balance drops from 85,000 to 18,820. Payroll alone accounts for 156,000 - more than half of all expenses.
B6: d) What 1-2 actions would you recommend to the CFO? This is fundamentally a working capital gap problem - the AR cycle runs longer than the AP/expense cycle. → Offer early-payment discounts to speed up collections, stay on top of follow-ups, and monitor customers' financial health so issues are caught early. Since this is a project-based business, labor costs (including ESOP) are the single largest line item - if the cash balance turns negative down the road, consider trimming bonuses.
B7: Key takeaway: Profit ≠ Cash. The timing mismatch between collections and disbursements has a massive impact on a company's real cash position.

Sheet Raw Data ->
K15: R

Sheet Cash Position
A1: Greenway Landscaping LLC
A2: Cash Position Summary
A4: Bank Name | B4: First National Bank
A5: Account Name | B5: Operating Checking
A6: Account Number | B6: Account 1010
A7: As of Date | B7: 11/30/2026
A8: Beginning Cash Balance | B8: 85000
A10: Note: Balance confirmed per bank statement dated 11/30/2026

Sheet AR Collections
A1: Greenway Landscaping LLC — Accounts Receivable
A2: As of November 30, 2026
A4: Customer Name | B4: Invoice # | C4: Invoice Date | D4: Due Date | E4: Amount | F4: Aging Bucket
A5: Maplewood HOA | B5: INV-2026-0441 | C5: 46327 | D5: 46359 | E5: 8500 | F5: 1-30 Days
A6: Crestview Commercial Park | B6: INV-2026-0442 | C6: 46331 | D6: 46361 | E6: 6200 | F6: 1-30 Days
A7: Riverside Estates | B7: INV-2026-0443 | C7: 46333 | D7: 46363 | E7: 7300 | F7: 1-30 Days
A8: City of Pinecrest - Parks | B8: INV-2026-0444 | C8: 46320 | D8: 46365 | E8: 9000 | F8: 31-60 Days
A9: Sunset Ridge HOA | B9: INV-2026-0445 | C9: 46338 | D9: 46368 | E9: 7000 | F9: 1-30 Days
A10: Harborview Condominiums | B10: INV-2026-0446 | C10: 46342 | D10: 46372 | E10: 7000 | F10: 1-30 Days
A11: Grand Pines Estate | B11: INV-2026-0447 | C11: 46347 | D11: 46375 | E11: 5000 | F11: 1-30 Days
A12: Thornwood Office Complex | B12: INV-2026-0448 | C12: 46348 | D12: 46380 | E12: 4000 | F12: 1-30 Days
A13: Lakewood Business Center | B13: INV-2026-0449 | C13: 46355 | D13: 46387 | E13: 9500 | F13: 1-30 Days
A14: Willowbrook HOA | B14: INV-2026-0450 | C14: 46357 | D14: 46389 | E14: 6500 | F14: Current
A15: Maplewood HOA | B15: INV-2026-0451 | C15: 46361 | D15: 46394 | E15: 3760 | F15: Current
A16: Riverside Estates | B16: INV-2026-0452 | C16: 46371 | D16: 46401 | E16: 6000 | F16: Current
... A28: Riverside Estates | B28: INV-2026-0464 | C28: 46415 | D28: 46445 | E28: 8000 | F28: Current
A29: TOTAL | E29: =SUM(E5:E28) -> 210760

Sheet Committed Expenses
A1: Greenway Landscaping LLC — Committed Expenses Schedule
A2: 13-Week Forecast Period: December 1, 2026 – February 28, 2027
A4: Expense Description | B4: Frequency | C4: Amount Per Occurrence | D4: Next Due Date | E4: Notes
A5: Payroll - Field & Office Staff | B5: Weekly (Fridays) | C5: 12000 | D5: 12/04/2026 | E5: Lương nhân viên; trả mỗi thứ Sáu
A6: Office & Yard Rent | B6: Monthly (1st) | C6: 8500 | D6: 12/01/2026 | E6: Thuê văn phòng + bãi xe; trả ngày 1
A7: Equipment Lease - Mowers & Trucks | B7: Monthly (15th) | C7: 3200 | D7: 12/15/2026 | E7: Thuê máy cắt cỏ & xe tải; đến Jun 2028
A8: Commercial General Liability Ins. | B8: Monthly (1st) | C8: 1800 | D8: 12/01/2026 | E8: Bảo hiểm trách nhiệm; Zenith Insurance
A9: Workers' Compensation Insurance | B9: Monthly (1st) | C9: 950 | D9: 12/01/2026 | E9: Bảo hiểm tai nạn LĐ; theo quy định bang
A10: Fuel & Fleet Operating Costs | B10: Weekly | C10: 2800 | D10: 12/05/2026 | E10: Nhiên liệu & vận hành; biến động theo việc
A11: Landscaping Materials & Supplies | B11: Bi-weekly | C11: 4500 | D11: 12/05/2026 | E11: Vật tư cảnh quan; đặt 2 tuần/lần
A12: SBA Term Loan Payment | B12: Monthly (20th) | C12: 2100 | D12: 12/20/2026 | E12: Khoản vay SBA-2023-4471; đáo hạn Dec 2030
A13: Utilities - Office & Yard | B13: Monthly (10th) | C13: 420 | D13: 12/10/2026 | E13: Điện, nước, internet
A14: Software & Subscriptions | B14: Monthly (1st) | C14: 310 | D14: 12/01/2026 | E14: ServiceTitan, QuickBooks, Microsoft 365
A15: Vehicle Registration & Permits | B15: Annual (Jan 15) | C15: 1200 | D15: 01/15/2027 | E15: Phí đăng ký xe; thường niên

Sheet Projection ->

Sheet Cash Outflow 
A1: CASH OUT BY WEEK
A3: Start Date | B3: =DATE(2026,12,1) -> 46357 | C3: =B3+7 -> 46364 | D3: =C3+7 -> 46371 | E3: =D3+7 -> 46378 | F3: =E3+7 -> 46385 | G3: =F3+7 -> 46392 | H3: =G3+7 -> 46399 | I3: =H3+7 -> 46406 | J3: =I3+7 -> 46413 | ... N3: =M3+7 -> 46441
A4: Expense/Week | B4: Week 01 | C4: Week 02 | D4: Week 03 | E4: Week 04 | F4: Week 05 | G4: Week 06 | H4: Week 07 | I4: Week 08 | J4: Week 09 | K4: Week 10 | L4: Week 11 | M4: Week 12 | N4: Week 13 | O4: Total
A5: ='Committed Expenses'!A5 -> Payroll - Field & Office Staff | B5: 12000 | C5: 12000 | D5: 12000 | E5: 12000 | F5: 12000 | G5: 12000 | H5: 12000 | I5: 12000 | J5: 12000 | K5: 12000 | L5: 12000 | M5: 12000 | N5: 12000 | O5: =SUM(B5:N5) -> 156000
A6: ='Committed Expenses'!A6 -> Office & Yard Rent | B6: 8500 | F6: 8500 | J6: 8500 | O6: =SUM(B6:N6) -> 25500
A7: ='Committed Expenses'!A7 -> Equipment Lease - Mowers & Trucks | D7: 3200 | H7: 3200 | L7: 3200 | O7: =SUM(B7:N7) -> 9600
A8: ='Committed Expenses'!A8 -> Commercial General Liability Ins. | B8: 1800 | F8: 1800 | J8: 1800 | O8: =SUM(B8:N8) -> 5400
A9: ='Committed Expenses'!A9 -> Workers' Compensation Insurance | B9: 950 | F9: 950 | J9: 950 | O9: =SUM(B9:N9) -> 2850
A10: ='Committed Expenses'!A10 -> Fuel & Fleet Operating Costs | B10: 2800 | C10: 2800 | D10: 2800 | E10: 2800 | F10: 2800 | G10: 2800 | H10: 2800 | I10: 2800 | J10: 2800 | K10: 2800 | L10: 2800 | M10: 2800 | N10: 2800 | O10: =SUM(B10:N10) -> 36400
A11: ='Committed Expenses'!A11 -> Landscaping Materials & Supplies | B11: 4500 | D11: 4500 | F11: 4500 | H11: 4500 | J11: 4500 | L11: 4500 | N11: 4500 | O11: =SUM(B11:N11) -> 31500
A12: ='Committed Expenses'!A12 -> SBA Term Loan Payment | D12: 2100 | I12: 2100 | M12: 2100 | O12: =SUM(B12:N12) -> 6300
A13: ='Committed Expenses'!A13 -> Utilities - Office & Yard | C13: 420 | G13: 420 | L13: 420 | O13: =SUM(B13:N13) -> 1260
A14: ='Committed Expenses'!A14 -> Software & Subscriptions | B14: 310 | F14: 310 | J14: 310 | O14: =SUM(B14:N14) -> 930
A15: ='Committed Expenses'!A15 -> Vehicle Registration & Permits | H15: 1200 | O15: =SUM(B15:N15) -> 1200
A16: TOTAL | B16: =SUM(B5:B15) -> 30860 | C16: =SUM(C5:C15) -> 15220 | D16: =SUM(D5:D15) -> 24600 | E16: =SUM(E5:E15) -> 14800 | F16: =SUM(F5:F15) -> 30860 | G16: =SUM(G5:G15) -> 15220 | H16: =SUM(H5:H15) -> 23700 | I16: =SUM(I5:I15) -> 16900 | ... N16: =SUM(N5:N15) -> 19300
B18: Cash Outflow
A19: {=TRANSPOSE(B4:N4)} -> Week 01 | B19: {=TRANSPOSE(B16:N16)} -> 30860
A20: Week 02 | B20: 15220
A21: Week 03 | B21: 24600
A22: Week 04 | B22: 14800
A23: Week 05 | B23: 30860
A24: Week 06 | B24: 15220
A25: Week 07 | B25: 23700
A26: Week 08 | B26: 16900
A27: Week 09 | B27: 30860
A28: Week 10 | B28: 14800
A29: Week 11 | B29: 22920
A30: Week 12 | B30: 16900
A31: Week 13 | B31: 19300

Sheet Cash Inflow
A1: AR Collections by Week
A2: Week | B2: Start date | C2: End date | D2: AR Collections
A3: Week 01 | B3: =DATE(2026,12,1) -> 46357 | C3: =B3+6 -> 46363 | D3: =SUMIFS('AR Collections'!$E$5:$E$28,'AR Collections'!$D$5:$D$28,"<="&C3) -> 22000
A4: Week 02 | B4: =C3+1 -> 46364 | C4: =B4+6 -> 46370 | D4: =SUMIFS('AR Collections'!$E$5:$E$28,'AR Collections'!$D$5:$D$28,"<="&C4)-SUM($D$3:D3) -> 16000
A5: Week 03 | B5: =C4+1 -> 46371 | C5: =B5+6 -> 46377 | D5: =SUMIFS('AR Collections'!$E$5:$E$28,'AR Collections'!$D$5:$D$28,"<="&C5)-SUM($D$3:D4) -> 12000
A6: Week 04 | B6: =C5+1 -> 46378 | C6: =B6+6 -> 46384 | D6: =SUMIFS('AR Collections'!$E$5:$E$28,'AR Collections'!$D$5:$D$28,"<="&C6)-SUM($D$3:D5) -> 4000
A7: Week 05 | B7: =C6+1 -> 46385 | C7: =B7+6 -> 46391 | D7: =SUMIFS('AR Collections'!$E$5:$E$28,'AR Collections'!$D$5:$D$28,"<="&C7)-SUM($D$3:D6) -> 16000
A8: Week 06 | B8: =C7+1 -> 46392 | C8: =B8+6 -> 46398 | D8: =SUMIFS('AR Collections'!$E$5:$E$28,'AR Collections'!$D$5:$D$28,"<="&C8)-SUM($D$3:D7) -> 3760
A9: Week 07 | B9: =C8+1 -> 46399 | C9: =B9+6 -> 46405 | D9: =SUMIFS('AR Collections'!$E$5:$E$28,'AR Collections'!$D$5:$D$28,"<="&C9)-SUM($D$3:D8) -> 6000
A10: Week 08 | B10: =C9+1 -> 46406 | C10: =B10+6 -> 46412 | D10: =SUMIFS('AR Collections'!$E$5:$E$28,'AR Collections'!$D$5:$D$28,"<="&C10)-SUM($D$3:D9) -> 24000
A11: Week 09 | B11: =C10+1 -> 46413 | C11: =B11+6 -> 46419 | D11: =SUMIFS('AR Collections'!$E$5:$E$28,'AR Collections'!$D$5:$D$28,"<="&C11)-SUM($D$3:D10) -> 31000
A12: Week 10 | B12: =C11+1 -> 46420 | C12: =B12+6 -> 46426 | D12: =SUMIFS('AR Collections'!$E$5:$E$28,'AR Collections'!$D$5:$D$28,"<="&C12)-SUM($D$3:D11) -> 16000
A13: Week 11 | B13: =C12+1 -> 46427 | C13: =B13+6 -> 46433 | D13: =SUMIFS('AR Collections'!$E$5:$E$28,'AR Collections'!$D$5:$D$28,"<="&C13)-SUM($D$3:D12) -> 24000
A14: Week 12 | B14: =C13+1 -> 46434 | C14: =B14+6 -> 46440 | D14: =SUMIFS('AR Collections'!$E$5:$E$28,'AR Collections'!$D$5:$D$28,"<="&C14)-SUM($D$3:D13) -> 16000
A15: Week 13 | B15: =C14+1 -> 46441 | C15: =B15+6 -> 46447 | D15: =SUMIFS('AR Collections'!$E$5:$E$28,'AR Collections'!$D$5:$D$28,"<="&C15)-SUM($D$3:D14) -> 20000
A16: TOTAL | D16: =SUM(D3:D15) -> 210760

Sheet Pivot Table
B2: Row Labels | C2: Sum of Cash In | D2: Sum of Cash Out | F2: Row Labels | G2: Beginning Balance | H2: Ending Balance | J2: Row Labels | K2: Sum of Net Cash Flow | M2: Expense/Week | N2: Total | P2: Expense/Week | Q2: Office & Yard Rent
B3: Week 01 | C3: 22000 | D3: 30860 | F3: Week 01 | G3: 85000 | H3: 76140 | J3: Week 01 | K3: -8860 | M3: Payroll - Field & Office Staff | N3: 156000
B4: Week 02 | C4: 16000 | D4: 15220 | F4: Week 02 | G4: 76140 | H4: 76920 | J4: Week 02 | K4: 780 | M4: Office & Yard Rent | N4: 25500 | P4: Sum of Total
B5: Week 03 | C5: 12000 | D5: 24600 | F5: Week 03 | G5: 76920 | H5: 64320 | J5: Week 03 | K5: -12600 | M5: Equipment Lease - Mowers & Trucks | N5: 9600 | P5: 25500
B6: Week 04 | C6: 4000 | D6: 14800 | F6: Week 04 | G6: 64320 | H6: 53520 | J6: Week 04 | K6: -10800 | M6: Commercial General Liability Ins. | N6: 5400
B7: Week 05 | C7: 16000 | D7: 30860 | F7: Week 05 | G7: 53520 | H7: 38660 | J7: Week 05 | K7: -14860 | M7: Workers' Compensation Insurance | N7: 2850
B8: Week 06 | C8: 3760 | D8: 15220 | F8: Week 06 | G8: 38660 | H8: 27200 | J8: Week 06 | K8: -11460 | M8: Fuel & Fleet Operating Costs | N8: 36400
B9: Week 07 | C9: 6000 | D9: 23700 | F9: Week 07 | G9: 27200 | H9: 9500 | J9: Week 07 | K9: -17700 | M9: Landscaping Materials & Supplies | N9: 31500
B10: Week 08 | C10: 24000 | D10: 16900 | F10: Week 08 | G10: 9500 | H10: 16600 | J10: Week 08 | K10: 7100 | M10: SBA Term Loan Payment | N10: 6300
B11: Week 09 | C11: 31000 | D11: 30860 | F11: Week 09 | G11: 16600 | H11: 16740 | J11: Week 09 | K11: 140 | M11: Utilities - Office & Yard | N11: 1260
B12: Week 10 | C12: 16000 | D12: 14800 | F12: Week 10 | G12: 16740 | H12: 17940 | J12: Week 10 | K12: 1200 | M12: Software & Subscriptions | N12: 930
B13: Week 11 | C13: 24000 | D13: 22920 | F13: Week 11 | G13: 17940 | H13: 19020 | J13: Week 11 | K13: 1080 | M13: Vehicle Registration & Permits | N13: 1200
B14: Week 12 | C14: 16000 | D14: 16900 | F14: Week 12 | G14: 19020 | H14: 18120 | J14: Week 12 | K14: -900
B15: Week 13 | C15: 20000 | D15: 19300 | F15: Week 13 | G15: 18120 | H15: 18820 | J15: Week 13 | K15: 700
B16: Grand Total | C16: 210760 | D16: 276940 | F16: Grand Total | G16: 519680 | H16: 453500 | J16: Grand Total | K16: -66180
C18: Cash Inflow | D18: Cash Outflow | G18: Beginning Balance | H18: Ending Balance | K18: Net Cash Flow
C19: =GETPIVOTDATA("Sum of Cash In",$B$2) -> 210760 | D19: =GETPIVOTDATA("Sum of Cash Out",$B$2) -> 276940 | G19: =GETPIVOTDATA("Sum of Beginning",$F$2) -> #REF! | H19: =GETPIVOTDATA("Sum of Ending",$F$2) -> #REF! | K19: =GETPIVOTDATA("Net Cash Flow",$J$2) -> -66180
